HISTORY.rst
MANIFEST.in
README.rst
setup.cfg
setup.py
Products/__init__.py
Products.ZMIntrospection.egg-info/PKG-INFO
Products.ZMIntrospection.egg-info/SOURCES.txt
Products.ZMIntrospection.egg-info/dependency_links.txt
Products.ZMIntrospection.egg-info/namespace_packages.txt
Products.ZMIntrospection.egg-info/not-zip-safe
Products.ZMIntrospection.egg-info/requires.txt
Products.ZMIntrospection.egg-info/top_level.txt
Products/ZMIntrospection/TODO.txt
Products/ZMIntrospection/__init__.py
Products/ZMIntrospection/tests/__init__.py
Products/ZMIntrospection/tests/testTab.py
Products/ZMIntrospection/zmi/manage_introspection.dtml