Metadata-Version: 2.1
Name: Products.ZMIntrospection
Version: 1.3
Summary: Append an Introspection tab to an object's management tabs.
Home-page: https://github.com/eea/Products.ZMIntrospection/
Author: Stefane Fermigier
Author-email: sf@nuxeo.com
License: GPL
Classifier: Framework :: Zope2
Classifier: Intended Audience :: Developers
Classifier: Development Status :: 6 - Mature
Requires-Dist: setuptools
